{
  "db_name": "PostgreSQL",
  "query": "SELECT state, ttl FROM sessions WHERE id = $1",
  "describe": {
    "columns": [
      {
        "ordinal": 0,
        "name": "state",
        "type_info": "Bytea"
      },
      {
        "ordinal": 1,
        "name": "ttl",
        "type_info": "Int8"
      }
    ],
    "parameters": {
      "Left": [
        "Text"
      ]
    },
    "nullable": [
      false,
      false
    ]
  },
  "hash": "08acb208bdd67cee85f40164cce0d4e8bee2ace211890a0f885684438c0b3c22"
}
